[
    {
        "type": "directory",
        "name": "atmosphere",
        "children": [
            {
                "type": "file",
                "name": "reboot_payload.bin",
                "checksum": "f451cde3e76e7019b47eeab9ca010179"
            }
        ]
    },
    {
        "type": "directory",
        "name": "bootloader",
        "children": [
            {
                "type": "directory",
                "name": "payloads",
                "children": [
                    {
                        "type": "file",
                        "name": "fusee.bin",
                        "checksum": "3b64530c63f11cdabe93f3e7dfea3bc4"
                    }
                ]
            },
            {
                "type": "file",
                "name": "update.bin",
                "checksum": "f451cde3e76e7019b47eeab9ca010179"
            }
        ]
    },
    {
        "type": "file",
        "name": "payload.bin",
        "checksum": "f451cde3e76e7019b47eeab9ca010179"
    }
]